README.md
setup.py
Flask_Ethereum.egg-info/PKG-INFO
Flask_Ethereum.egg-info/SOURCES.txt
Flask_Ethereum.egg-info/dependency_links.txt
Flask_Ethereum.egg-info/not-zip-safe
Flask_Ethereum.egg-info/requires.txt
Flask_Ethereum.egg-info/top_level.txt
flask_ethereum/__init__.py
flask_ethereum/core.py